sage/kernel/__init__.py
sage/kernel/_version.py
sage/kernel/api/__init__.py
sage/kernel/api/base_environment.py
sage/kernel/api/connected_streams.py
sage/kernel/api/datastream.py
sage/kernel/api/local_environment.py
sage/kernel/api/remote_environment.py
sage/kernel/api/function/__init__.py
sage/kernel/api/function/simple_batch_function.py
sage/kernel/api/operator/__init__.py
sage/kernel/api/operator/base_operator.py
sage/kernel/api/operator/batch_operator.py
sage/kernel/api/operator/comap_operator.py
sage/kernel/api/operator/filter_operator.py
sage/kernel/api/operator/flatmap_operator.py
sage/kernel/api/operator/future_operator.py
sage/kernel/api/operator/join_operator.py
sage/kernel/api/operator/keyby_operator.py
sage/kernel/api/operator/map_operator.py
sage/kernel/api/operator/sink_operator.py
sage/kernel/api/operator/source_operator.py
sage/kernel/api/service/__init__.py
sage/kernel/api/service/base_service.py
sage/kernel/api/service/pipeline_service/__init__.py
sage/kernel/api/service/pipeline_service/pipeline_bridge.py
sage/kernel/api/service/pipeline_service/pipeline_service.py
sage/kernel/api/service/pipeline_service/pipeline_sink.py
sage/kernel/api/service/pipeline_service/pipeline_source.py
sage/kernel/api/transformation/__init__.py
sage/kernel/api/transformation/base_transformation.py
sage/kernel/api/transformation/batch_transformation.py
sage/kernel/api/transformation/comap_transformation.py
sage/kernel/api/transformation/filter_transformation.py
sage/kernel/api/transformation/flatmap_transformation.py
sage/kernel/api/transformation/future_transformation.py
sage/kernel/api/transformation/join_transformation.py
sage/kernel/api/transformation/keyby_transformation.py
sage/kernel/api/transformation/map_transformation.py
sage/kernel/api/transformation/sink_transformation.py
sage/kernel/api/transformation/source_transformation.py
sage/kernel/core/__init__.py
sage/kernel/core/constants.py
sage/kernel/core/exceptions.py
sage/kernel/core/types.py
isage_kernel-0.2.4.6.dist-info/METADATA
isage_kernel-0.2.4.6.dist-info/WHEEL
isage_kernel-0.2.4.6.dist-info/top_level.txt
isage_kernel-0.2.4.6.dist-info/RECORD
