Metadata-Version: 2.4
Name: isage-kernel
Version: 0.2.4.6
Summary: SAGE Kernel Module - Streaming-Augmented Generative Execution
Author-email: IntelliStream Team <shuhao_zhang@hust.edu.cn>
License: MIT
Project-URL: Homepage, https://github.com/intellistream/SAGE
Project-URL: Repository, https://github.com/intellistream/SAGE.git
Project-URL: Documentation, https://intellistream.github.io/SAGE-Pub/
Project-URL: Issues, https://github.com/intellistream/SAGE/issues
Keywords: data,reasoning,kernel,dataflow,llm,ml,framework,rag,intellistream,cli,ai,sage
Classifier: Development Status :: 4 - Beta
Classifier: Intended Audience :: Developers
Classifier: Intended Audience :: Science/Research
Classifier: Operating System :: OS Independent
Classifier: Topic :: Scientific/Engineering :: Artificial Intelligence
Classifier: Topic :: Software Development :: Libraries :: Python Modules
Classifier: Topic :: System :: Distributed Computing
Requires-Python: >=3.10
Provides-Extra: dev
Requires-Dist: pytest>=7.0.0; extra == "dev"
Requires-Dist: pytest-cov>=4.0.0; extra == "dev"
Requires-Dist: pytest-asyncio>=0.21.0; extra == "dev"
Requires-Dist: pytest-benchmark>=4.0.0; extra == "dev"
Requires-Dist: ruff==0.14.6; extra == "dev"
Requires-Dist: mypy>=1.7.0; extra == "dev"
Provides-Extra: ml
Requires-Dist: torch<3.0.0,>=2.7.0; extra == "ml"
Requires-Dist: torchvision<1.0.0,>=0.22.0; extra == "ml"
Provides-Extra: server
Requires-Dist: fastapi<1.0.0,>=0.115.0; extra == "server"
Requires-Dist: uvicorn[standard]<1.0.0,>=0.34.0; extra == "server"
Requires-Dist: python_multipart<0.1.0,>=0.0.20; extra == "server"
Provides-Extra: distributed
Requires-Dist: ray<3.0.0,>=2.48.0; extra == "distributed"
Requires-Dist: grpcio<2.0.0,>=1.74.0; extra == "distributed"
Requires-Dist: protobuf<7.0.0,>=6.32.0; extra == "distributed"
Requires-Dist: msgpack<2.0.0,>=1.1.0; extra == "distributed"
Provides-Extra: aws
Requires-Dist: aioboto3<15.0.0,>=14.1.0; extra == "aws"
Provides-Extra: cli
Requires-Dist: typer<1.0.0,>=0.15.0; extra == "cli"
Requires-Dist: rich<14.0.0,>=13.0.0; extra == "cli"
Requires-Dist: click<9.0.0,>=8.0.0; extra == "cli"
Requires-Dist: questionary<2.0.0,>=1.10.0; extra == "cli"
Requires-Dist: prompt_toolkit<4.0.0,>=3.0.50; extra == "cli"
Requires-Dist: tabulate<1.0.0,>=0.9.0; extra == "cli"
Provides-Extra: build
Requires-Dist: Cython<4.0.0,>=3.1.0; extra == "build"
Requires-Dist: pybind11<4.0.0,>=3.0.0; extra == "build"
Provides-Extra: all
Requires-Dist: isage-kernel[aws,build,cli,distributed,ml,server]; extra == "all"
